{
  "project_info": {
    "project_number": "725108780385",
    "project_id": "tareatick-cbc8c",
    "storage_bucket": "tareatick-cbc8c.appspot.com"
  },
  "client": [
    {
      "client_info": {
        "mobilesdk_app_id": "1:725108780385:android:1762055f0288b177d5a920",
        "android_client_info": {
          "package_name": "com.stomas.evafinal"
        }
      },
      "oauth_client": [],
      "api_key": [
        {
          "current_key": "AIzaSyCOaLdWDqAZCkoWEnypq_zK4eDy8Ufb7XA"
        }
      ],
      "services": {
        "appinvite_service": {
          "other_platform_oauth_client": []
        }
      }
    }
  ],
  "configuration_version": "1"
}